{
  "generator-jhipster": {
    "applicationType": "monolith",
    "authenticationType": "jwt",
    "baseName": "JuntosnaGranaApplication",
    "blueprints": [],
    "buildTool": "maven",
    "cacheProvider": "hazelcast",
    "clientFramework": "angular",
    "clientPackageManager": "npm",
    "creationTimestamp": 1752242352335,
    "databaseType": "sql",
    "devDatabaseType": "h2Disk",
    "enableHibernateCache": true,
    "enableSwaggerCodegen": false,
    "enableTranslation": true,
    "entities": [],
    "gitCompany": "",
    "iaCTools": ["bicep", "terraform"],
    "jhiPrefix": "jhi",
    "jhipsterVersion": "8.11.0",
    "jwtSecretKey": "NDliMTFjZWMzNmQ0OTUyNTJjZWFkNDUwMjkxYTc2YjZmZDIxYjJiNWFmNjM4ZGIzNjI4YzExODE2MzU4NDBiNjNmYTAxNTEwOTNiN2UwM2UzOWRlYmE4YzRiYWRhZGViYjA5ODNjZjA4NTQ1ZGU2YWFjM2ZkZTZiMDU2OTQ3Njk=",
    "languages": ["pt-br"],
    "messageBroker": false,
    "nativeLanguage": "pt-br",
    "packageFolder": "com/noxius/juntosnagrana",
    "packageName": "com.noxius.juntosnagrana",
    "prodDatabaseType": "postgresql",
    "searchEngine": false,
    "serverPort": 8080,
    "serviceDiscoveryType": "consul",
    "testFrameworks": [],
    "useSass": true,
    "websocket": false,
    "withAdminUi": false
  },
  "git-company": "lviegas21",
  "git-provider": "GitHub",
  "repository-name": "juntos-na-grana-backend"
}
